pycsa/__init__.py
pycsa/algorithm.py
pycsa-0.1.3.dist-info/DESCRIPTION.rst
pycsa-0.1.3.dist-info/METADATA
pycsa-0.1.3.dist-info/RECORD
pycsa-0.1.3.dist-info/WHEEL
pycsa-0.1.3.dist-info/metadata.json
pycsa-0.1.3.dist-info/top_level.txt
