Metadata-Version: 2.0
Name: pycsa
Version: 0.1.3
Summary: Python implementation of coupled simulated annealing (CSA)
Home-page: https://github.com/structurely/csa
Author: Boudhayan Banerjee, Evan 'Pete' Walsh
Author-email: ronnie@structurely.com, epwalsh@structurely.com
License: UNKNOWN
Keywords: csa,sa,simulated annealing,annealing,coupled simulated annealing
Platform: UNKNOWN
Classifier: Development Status :: 3 - Alpha
Classifier: Intended Audience :: Science/Research
Classifier: Operating System :: OS Independent
Classifier: Programming Language :: Python :: 2.7
Classifier: Programming Language :: Python :: 3.5
Classifier: Topic :: Scientific/Engineering
